AUTHORS.rst
CONTRIBUTING.rst
LICENSE
MANIFEST.in
README.rst
setup.cfg
setup.py
stackdio/__init__.py
stackdio/api/__init__.py
stackdio/api/urls.py
stackdio/api/blueprints/__init__.py
stackdio/api/blueprints/admin.py
stackdio/api/blueprints/api.py
stackdio/api/blueprints/filters.py
stackdio/api/blueprints/mixins.py
stackdio/api/blueprints/models.py
stackdio/api/blueprints/permissions.py
stackdio/api/blueprints/serializers.py
stackdio/api/blueprints/urls.py
stackdio/api/blueprints/validators.py
stackdio/api/blueprints/migrations/0001_initial.py
stackdio/api/blueprints/migrations/0002_v0_7_migrations.py
stackdio/api/blueprints/migrations/0003_v0_7b_migrations.py
stackdio/api/blueprints/migrations/0004_v0_7c_migrations.py
stackdio/api/blueprints/migrations/0005_v0_7d_migrations.py
stackdio/api/blueprints/migrations/__init__.py
stackdio/api/blueprints/tests/__init__.py
stackdio/api/cloud/__init__.py
stackdio/api/cloud/admin.py
stackdio/api/cloud/api.py
stackdio/api/cloud/filters.py
stackdio/api/cloud/mixins.py
stackdio/api/cloud/models.py
stackdio/api/cloud/permissions.py
stackdio/api/cloud/serializers.py
stackdio/api/cloud/urls.py
stackdio/api/cloud/utils.py
stackdio/api/cloud/fixtures/initial_data.json
stackdio/api/cloud/migrations/0001_initial.py
stackdio/api/cloud/migrations/0002_initial.py
stackdio/api/cloud/migrations/0003_initial_data.py
stackdio/api/cloud/migrations/0004_v0_7_migrations.py
stackdio/api/cloud/migrations/0005_v0_7b_migrations.py
stackdio/api/cloud/migrations/0006_v0_7c_migrations.py
stackdio/api/cloud/migrations/0007_v0_7d_migrations.py
stackdio/api/cloud/migrations/0008_v0_7e_migrations.py
stackdio/api/cloud/migrations/__init__.py
stackdio/api/cloud/providers/__init__.py
stackdio/api/cloud/providers/aws.py
stackdio/api/cloud/providers/base.py
stackdio/api/cloud/providers/rackspace.py
stackdio/api/cloud/tests/__init__.py
stackdio/api/cloud/tests/integration.py
stackdio/api/formulas/__init__.py
stackdio/api/formulas/admin.py
stackdio_server.egg-info/PKG-INFO
stackdio_server.egg-info/SOURCES.txt
stackdio_server.egg-info/dependency_links.txt
stackdio_server.egg-info/entry_points.txt
stackdio_server.egg-info/not-zip-safe
stackdio_server.egg-info/requires.txt
stackdio_server.egg-info/top_level.txt