Metadata-Version: 1.1
Name: stackdio-server
Version: 0.7.7
Summary: A cloud deployment, automation, and orchestration platform for everyone.
Home-page: http://stackd.io
Author: Digital Reasoning Systems, Inc.
Author-email: info@stackd.io
License: Apache 2.0
Platform: UNKNOWN
Classifier: Development Status :: 4 - Beta
Classifier: Environment :: Web Environment
Classifier: Framework :: Django
Classifier: Framework :: Django :: 1.8
Classifier: Intended Audience :: Developers
Classifier: Intended Audience :: Information Technology
Classifier: Intended Audience :: System Administrators
Classifier: License :: OSI Approved :: Apache Software License
Classifier: Operating System :: POSIX :: Linux
Classifier: Programming Language :: Python
Classifier: Programming Language :: Python :: 2
Classifier: Programming Language :: Python :: 2.7
Classifier: Programming Language :: Python :: 2 :: Only
Classifier: Topic :: System :: Clustering
Classifier: Topic :: System :: Distributed Computing
